{"metadata":{"asset_id":"e977c341-57c5-4092-a339-efb4de6bc9bd","asset_attributes":["data_asset"],"name":"aavail-streams.csv","asset_type":"data_asset","created_at":"2020-05-05T00:32:47Z","description":"","origin_country":"us","owner_id":"1000330999","project_id":"6c0e3d3e-91f8-41be-a8b2-8933d390ccfd","sandbox_id":"6c0e3d3e-91f8-41be-a8b2-8933d390ccfd","size":435744,"tags":[],"usage":{"last_update_time":1588638768069,"last_updated_at":"2020-05-05T00:32:48Z"}},"entity":{"data_asset":{"mime_type":"text/csv","dataset":false}},"attachments":[{"id":"4743a370-ab26-4aa0-9c3e-5df88ad24af2","version":2,"asset_type":"data_asset","name":"aavail-streams.csv","mime":"text/csv","object_key":"data_asset/aavail-streams.csv","create_time":1588638768068,"size":435744,"is_remote":false,"is_managed":false,"is_referenced":true,"is_object_key_read_only":true,"is_user_provided_path_key":true,"transfer_complete":true,"is_partitioned":false,"complete_time_ticks":1588638768068,"user_data":{},"test_doc":0,"handle":{"key":"data_asset/aavail-streams.csv","upload_id":"done","max_part_num":1},"usage":{"access_count":0,"last_accessor_id":"1000330999","last_access_time":1588638768068}}]}